{"MUSIC2001": {"url": "https://www.gla.ac.uk/coursecatalogue/course/?code=MUSIC2001", "title": "Aesthetics And Philosophy Of Music (APM) MUSIC2001"}, "MUSIC2006": {"url": "https://www.gla.ac.uk/coursecatalogue/course/?code=MUSIC2006", "title": "Musical Techniques, Foundation (MA/BEng) MUSIC2006"}, "MUSIC2007": {"url": "https://www.gla.ac.uk/coursecatalogue/course/?code=MUSIC2007", "title": "Musical Techniques, Intermediate MUSIC2007"}, "MUSIC5082": {"url": "https://www.gla.ac.uk/coursecatalogue/course/?code=MUSIC5082", "title": "Composition, Digital and Creative Skills MUSIC5082"}, "MUSIC5080": {"url": "https://www.gla.ac.uk/coursecatalogue/course/?code=MUSIC5080", "title": "Notation and Performance Practice MUSIC5080"}, "MUSIC2004": {"url": "https://www.gla.ac.uk/coursecatalogue/course/?code=MUSIC2004", "title": "Bach and the Lutheran Passion MUSIC2004"}, "MUSIC5084": {"url": "https://www.gla.ac.uk/coursecatalogue/course/?code=MUSIC5084", "title": "Individual Creative Practice MUSIC5084"}, "MUSIC2005": {"url": "https://www.gla.ac.uk/coursecatalogue/course/?code=MUSIC2005", "title": "Introduction to Composition MUSIC2005"}, "MUSIC1021": {"url": "https://www.gla.ac.uk/coursecatalogue/course/?code=MUSIC1021", "title": "Listening through Analysis MUSIC1021"}, "MUSIC1020": {"url": "https://www.gla.ac.uk/coursecatalogue/course/?code=MUSIC1020", "title": "Listening in Culture MUSIC1020"}, "MUSIC5003": {"url": "https://www.gla.ac.uk/coursecatalogue/course/?code=MUSIC5003", "title": "Creative Practice 1 MUSIC5003"}, "MUSIC5006": {"url": "https://www.gla.ac.uk/coursecatalogue/course/?code=MUSIC5006", "title": "Musicology MUSIC5006"}, "MUSIC5004": {"url": "https://www.gla.ac.uk/coursecatalogue/course/?code=MUSIC5004", "title": "Creative Practice 2 MUSIC5004"}, "MUSIC5061": {"url": "https://www.gla.ac.uk/coursecatalogue/course/?code=MUSIC5061", "title": "Current Issues in Musicology MUSIC5061"}, "MUSIC5060": {"url": "https://www.gla.ac.uk/coursecatalogue/course/?code=MUSIC5060", "title": "Introduction to Musicology MUSIC5060"}, "MUSIC5062": {"url": "https://www.gla.ac.uk/coursecatalogue/course/?code=MUSIC5062", "title": "Research Skills and Digital Musicology MUSIC5062"}, "MUSIC4013P": {"url": "https://www.gla.ac.uk/coursecatalogue/course/?code=MUSIC4013P", "title": "Dissertation MUSIC4013P"}, "MUSIC4028": {"url": "https://www.gla.ac.uk/coursecatalogue/course/?code=MUSIC4028", "title": "Performance Level 4 (Advanced) MUSIC4028"}, "MUSIC4029": {"url": "https://www.gla.ac.uk/coursecatalogue/course/?code=MUSIC4029", "title": "Performance (Intermediate, MA) MUSIC4029"}, "MUSIC4022": {"url": "https://www.gla.ac.uk/coursecatalogue/course/?code=MUSIC4022", "title": "OPERA (MA/BENG/BMUSHONS) MUSIC4022"}, "MUSIC4020": {"url": "https://www.gla.ac.uk/coursecatalogue/course/?code=MUSIC4020", "title": "Musical Techniques, Intermediate (MA/BEng Hons) MUSIC4020"}, "MUSIC5078": {"url": "https://www.gla.ac.uk/coursecatalogue/course/?code=MUSIC5078", "title": "Historiography & Criticism MUSIC5078"}, "MUSIC5079": {"url": "https://www.gla.ac.uk/coursecatalogue/course/?code=MUSIC5079", "title": "The Music of Scotland MUSIC5079"}, "MUSIC5077": {"url": "https://www.gla.ac.uk/coursecatalogue/course/?code=MUSIC5077", "title": "Genders MUSIC5077"}, "MUSIC4011": {"url": "https://www.gla.ac.uk/coursecatalogue/course/?code=MUSIC4011", "title": "Introduction to Composition for Honours MUSIC4011"}, "MUSIC4014": {"url": "https://www.gla.ac.uk/coursecatalogue/course/?code=MUSIC4014", "title": "Advanced Research Project (BMus only) MUSIC4014"}, "MUSIC4090": {"url": "https://www.gla.ac.uk/coursecatalogue/course/?code=MUSIC4090", "title": "Performance (Higher) MUSIC4090"}, "MUSIC2011": {"url": "https://www.gla.ac.uk/coursecatalogue/course/?code=MUSIC2011", "title": "Sonic Arts, Intermediate MUSIC2011"}, "MUSIC5037P": {"url": "https://www.gla.ac.uk/coursecatalogue/course/?code=MUSIC5037P", "title": "HIPP Dissertation (major) MUSIC5037P"}, "MUSIC2014": {"url": "https://www.gla.ac.uk/coursecatalogue/course/?code=MUSIC2014", "title": "Romantic Song MUSIC2014"}, "MUSIC5042": {"url": "https://www.gla.ac.uk/coursecatalogue/course/?code=MUSIC5042", "title": "HIPP Seminar 2 MUSIC5042"}, "MUSIC5041": {"url": "https://www.gla.ac.uk/coursecatalogue/course/?code=MUSIC5041", "title": "HIPP Seminar 1 MUSIC5041"}, "MUSIC5040": {"url": "https://www.gla.ac.uk/coursecatalogue/course/?code=MUSIC5040", "title": "HIPP Practical Presentation MUSIC5040"}, "MUSIC4038": {"url": "https://www.gla.ac.uk/coursecatalogue/course/?code=MUSIC4038", "title": "Romantic Song (MA/BEng Hons) MUSIC4038"}, "MUSIC4004": {"url": "https://www.gla.ac.uk/coursecatalogue/course/?code=MUSIC4004", "title": "BACH AND THE LUTHERAN PASSION (MA/BENG HONS) MUSIC4004"}, "MUSIC5083P": {"url": "https://www.gla.ac.uk/coursecatalogue/course/?code=MUSIC5083P", "title": "Composition Portfolio MUSIC5083P"}, "MUSIC4001": {"url": "https://www.gla.ac.uk/coursecatalogue/course/?code=MUSIC4001", "title": "Aesthetics And Philosophy Of Music (MA/BEng Hons) MUSIC4001"}, "MUSIC4002": {"url": "https://www.gla.ac.uk/coursecatalogue/course/?code=MUSIC4002", "title": "Analysis: Formalist Approaches (Honours) MUSIC4002"}, "MUSIC4003": {"url": "https://www.gla.ac.uk/coursecatalogue/course/?code=MUSIC4003", "title": "ASPECTS OF MODERNITY (ARTS) MUSIC4003"}, "MUSIC4008": {"url": "https://www.gla.ac.uk/coursecatalogue/course/?code=MUSIC4008", "title": "Composition, Advanced MUSIC4008"}, "MUSIC4088": {"url": "https://www.gla.ac.uk/coursecatalogue/course/?code=MUSIC4088", "title": "Modernist Music Aesthetics MUSIC4088"}, "MUSIC4089": {"url": "https://www.gla.ac.uk/coursecatalogue/course/?code=MUSIC4089", "title": "Musical Culture in the Long Nineteenth Century MUSIC4089"}, "MUSIC4084": {"url": "https://www.gla.ac.uk/coursecatalogue/course/?code=MUSIC4084", "title": "Sonic Arts: Interacting with Sound (MA/BMus Hons) MUSIC4084"}, "MUSIC4085": {"url": "https://www.gla.ac.uk/coursecatalogue/course/?code=MUSIC4085", "title": "Sonic Arts: Interactive Audiovisual Media MUSIC4085"}, "MUSIC4086": {"url": "https://www.gla.ac.uk/coursecatalogue/course/?code=MUSIC4086", "title": "Sonic Arts: Performance Project MUSIC4086"}, "MUSIC4087": {"url": "https://www.gla.ac.uk/coursecatalogue/course/?code=MUSIC4087", "title": "Sonic Arts: Sound for Narrative Film MUSIC4087"}, "MUSIC4080": {"url": "https://www.gla.ac.uk/coursecatalogue/course/?code=MUSIC4080", "title": "Performance Practice MUSIC4080"}, "MUSIC4081": {"url": "https://www.gla.ac.uk/coursecatalogue/course/?code=MUSIC4081", "title": "Popular Music Politics MUSIC4081"}, "MUSIC4082": {"url": "https://www.gla.ac.uk/coursecatalogue/course/?code=MUSIC4082", "title": "Research Internship in Music MUSIC4082"}, "MUSIC4083": {"url": "https://www.gla.ac.uk/coursecatalogue/course/?code=MUSIC4083", "title": "Sonic Arts: Individual Creative Project MUSIC4083"}, "MUSIC2002": {"url": "https://www.gla.ac.uk/coursecatalogue/course/?code=MUSIC2002", "title": "Analysis: Formalist Approaches MUSIC2002"}, "MUSIC2003": {"url": "https://www.gla.ac.uk/coursecatalogue/course/?code=MUSIC2003", "title": "ASPECTS OF MODERNITY (ENGINEERING) MUSIC2003"}, "MUSIC5052": {"url": "https://www.gla.ac.uk/coursecatalogue/course/?code=MUSIC5052", "title": "Sonic Art Aesthetics & Criticism MUSIC5052"}, "MUSIC5053": {"url": "https://www.gla.ac.uk/coursecatalogue/course/?code=MUSIC5053", "title": "Audiovisual Composition MUSIC5053"}, "MUSIC5054": {"url": "https://www.gla.ac.uk/coursecatalogue/course/?code=MUSIC5054", "title": "Creating with Technology MUSIC5054"}, "MUSIC5055": {"url": "https://www.gla.ac.uk/coursecatalogue/course/?code=MUSIC5055", "title": "Field Recording, Sound and Place MUSIC5055"}, "MUSIC5056": {"url": "https://www.gla.ac.uk/coursecatalogue/course/?code=MUSIC5056", "title": "Sonic Art Performance MUSIC5056"}, "MUSIC5057": {"url": "https://www.gla.ac.uk/coursecatalogue/course/?code=MUSIC5057", "title": "Sonic Arts Portfolio MUSIC5057"}, "MUSIC5058": {"url": "https://www.gla.ac.uk/coursecatalogue/course/?code=MUSIC5058", "title": "Sound Shaping and Design MUSIC5058"}, "MUSIC5059": {"url": "https://www.gla.ac.uk/coursecatalogue/course/?code=MUSIC5059", "title": "Sound Art in Dialogue MUSIC5059"}, "MUSIC5015P": {"url": "https://www.gla.ac.uk/coursecatalogue/course/?code=MUSIC5015P", "title": "Popular Music Studies Dissertation MUSIC5015P"}, "MUSIC2009": {"url": "https://www.gla.ac.uk/coursecatalogue/course/?code=MUSIC2009", "title": "Performance Level 2 (Intermediate) MUSIC2009"}, "MUSIC5081P": {"url": "https://www.gla.ac.uk/coursecatalogue/course/?code=MUSIC5081P", "title": "Dissertation in Musicology MUSIC5081P"}, "MUSIC4070": {"url": "https://www.gla.ac.uk/coursecatalogue/course/?code=MUSIC4070", "title": "Debussy and the 'Belle \u00e9poque' MUSIC4070"}, "MUSIC4073": {"url": "https://www.gla.ac.uk/coursecatalogue/course/?code=MUSIC4073", "title": "Film Music MUSIC4073"}, "MUSIC4072": {"url": "https://www.gla.ac.uk/coursecatalogue/course/?code=MUSIC4072", "title": "Experimental Music Practice MUSIC4072"}, "MUSIC4075": {"url": "https://www.gla.ac.uk/coursecatalogue/course/?code=MUSIC4075", "title": "Music Criticism in Theory and Practice MUSIC4075"}, "MUSIC4074": {"url": "https://www.gla.ac.uk/coursecatalogue/course/?code=MUSIC4074", "title": "Historiography of Music MUSIC4074"}, "MUSIC4077": {"url": "https://www.gla.ac.uk/coursecatalogue/course/?code=MUSIC4077", "title": "Notation MUSIC4077"}, "MUSIC4079": {"url": "https://www.gla.ac.uk/coursecatalogue/course/?code=MUSIC4079", "title": "Performance Advanced (40) MUSIC4079"}, "MUSIC4078": {"url": "https://www.gla.ac.uk/coursecatalogue/course/?code=MUSIC4078", "title": "Performance Advanced (20) MUSIC4078"}, "MUSIC2008": {"url": "https://www.gla.ac.uk/coursecatalogue/course/?code=MUSIC2008", "title": "Opera MUSIC2008"}, "MUSIC5024": {"url": "https://www.gla.ac.uk/coursecatalogue/course/?code=MUSIC5024", "title": "Music Research Seminar (B) MUSIC5024"}, "MUSIC5035P": {"url": "https://www.gla.ac.uk/coursecatalogue/course/?code=MUSIC5035P", "title": "HIPP Assessed Performance (major) MUSIC5035P"}, "MUSIC5020": {"url": "https://www.gla.ac.uk/coursecatalogue/course/?code=MUSIC5020", "title": "Composition Portfolio (A) MUSIC5020"}, "MUSIC5023": {"url": "https://www.gla.ac.uk/coursecatalogue/course/?code=MUSIC5023", "title": "Music Research Seminar (A) MUSIC5023"}, "MUSIC4076P": {"url": "https://www.gla.ac.uk/coursecatalogue/course/?code=MUSIC4076P", "title": "Music General Paper MUSIC4076P"}, "MUSIC4062": {"url": "https://www.gla.ac.uk/coursecatalogue/course/?code=MUSIC4062", "title": "Music of Scotland through the Long 18th Century - to start in 2017-18 MUSIC4062"}, "MUSIC4063": {"url": "https://www.gla.ac.uk/coursecatalogue/course/?code=MUSIC4063", "title": "Composition in the Classroom MUSIC4063"}, "MUSIC4060": {"url": "https://www.gla.ac.uk/coursecatalogue/course/?code=MUSIC4060", "title": "Genders (30) MUSIC4060"}, "MUSIC4061": {"url": "https://www.gla.ac.uk/coursecatalogue/course/?code=MUSIC4061", "title": "Introduction to Popular Culture MUSIC4061"}, "MUSIC4066": {"url": "https://www.gla.ac.uk/coursecatalogue/course/?code=MUSIC4066", "title": "Aspects of Modernity MUSIC4066"}, "MUSIC4067": {"url": "https://www.gla.ac.uk/coursecatalogue/course/?code=MUSIC4067", "title": "Composition Advanced 20 MUSIC4067"}, "MUSIC4065": {"url": "https://www.gla.ac.uk/coursecatalogue/course/?code=MUSIC4065", "title": "Analysis: Critical and Hermeneutic Approaches MUSIC4065"}, "MUSIC4068": {"url": "https://www.gla.ac.uk/coursecatalogue/course/?code=MUSIC4068", "title": "Composition Advanced 40 MUSIC4068"}, "MUSIC4069": {"url": "https://www.gla.ac.uk/coursecatalogue/course/?code=MUSIC4069", "title": "Composition Higher MUSIC4069"}, "MUSIC5036": {"url": "https://www.gla.ac.uk/coursecatalogue/course/?code=MUSIC5036", "title": "HIPP Assessed Performance (minor) MUSIC5036"}, "MUSIC1005": {"url": "https://www.gla.ac.uk/coursecatalogue/course/?code=MUSIC1005", "title": "Performance Level 1 (Foundation) MUSIC1005"}, "MUSIC1004": {"url": "https://www.gla.ac.uk/coursecatalogue/course/?code=MUSIC1004", "title": "Orchestration MUSIC1004"}, "MUSIC1002": {"url": "https://www.gla.ac.uk/coursecatalogue/course/?code=MUSIC1002", "title": "Musical Techniques, Foundation (BMus) MUSIC1002"}, "MUSIC5038": {"url": "https://www.gla.ac.uk/coursecatalogue/course/?code=MUSIC5038", "title": "HIPP Dissertation (minor) MUSIC5038"}, "MUSIC5039": {"url": "https://www.gla.ac.uk/coursecatalogue/course/?code=MUSIC5039", "title": "HIPP Practical Portfolio MUSIC5039"}, "MUSIC5021": {"url": "https://www.gla.ac.uk/coursecatalogue/course/?code=MUSIC5021", "title": "Composition Portfolio (B) MUSIC5021"}, "MUSIC4071P": {"url": "https://www.gla.ac.uk/coursecatalogue/course/?code=MUSIC4071P", "title": "Dissertation in Music MUSIC4071P"}, "MUSIC4059": {"url": "https://www.gla.ac.uk/coursecatalogue/course/?code=MUSIC4059", "title": "Genders (20) MUSIC4059"}, "MUSIC4048": {"url": "https://www.gla.ac.uk/coursecatalogue/course/?code=MUSIC4048", "title": "Jazz and Blues MUSIC4048"}, "MUSIC2020": {"url": "https://www.gla.ac.uk/coursecatalogue/course/?code=MUSIC2020", "title": "Jazz and Blues MUSIC2020"}, "MUSIC2021": {"url": "https://www.gla.ac.uk/coursecatalogue/course/?code=MUSIC2021", "title": "Musical Culture in the Long Nineteenth Century MUSIC2021"}, "MUSIC2022": {"url": "https://www.gla.ac.uk/coursecatalogue/course/?code=MUSIC2022", "title": "Sonic Arts: Interacting with Sound (BEng) MUSIC2022"}, "MUSIC2023": {"url": "https://www.gla.ac.uk/coursecatalogue/course/?code=MUSIC2023", "title": "Sonic Arts: Interacting with Sound (MA/BMus) MUSIC2023"}, "MUSIC2024": {"url": "https://www.gla.ac.uk/coursecatalogue/course/?code=MUSIC2024", "title": "Musical Techniques, Foundation Semester One MUSIC2024"}, "MUSIC2025": {"url": "https://www.gla.ac.uk/coursecatalogue/course/?code=MUSIC2025", "title": "Musical Techniques, Foundation Semester Two MUSIC2025"}}